{
  "data": [{
    "author":{
      "name":"Mingy Jongo",
      "image":"https://vignette.wikia.nocookie.net/banjokazooie/images/9/9a/Mingy-jongo.png"
    },
    "description":"Bzzarrgh!",
    "field":{
      "description":"I calculate my chances of stopping them are now minimal..."
    }
  },
  {
    "author":{
      "name":"Wozza", "image":"https://vignette.wikia.nocookie.net/banjokazooie/images/2/28/Wozza_icon.png"
    },
    "description":"Watch out for a smelly speedrunner and their brand new PB.",
    "field":{
      "description":"Eeep! Another speedrunner!"
    }
  },
  {
    "author":{
      "name":"Snacker", "image":"https://vignette.wikia.nocookie.net/banjokazooie/images/b/b5/Snacker%27s_Head_Icon.png"
    },
    "description":"Snacker smells tasty new PB, stay just there!",
    "field":{
      "description":"Mmmm...lovely!"
    }
  },
  {
    "author":{
      "name":"Klungo", "image":"https://vignette.wikia.nocookie.net/banjokazooie/images/8/80/Klungo_icon.png"
    },
    "description":"Klungo clever, learn lotsss. Hasss learnt of new PB!",
    "field":{
      "description":"Ssstupid ssspeedrunner bopped poor Klungo!"
    }
  },    
  {
    "author":{
      "name":"Gobi", "image":"https://vignette.wikia.nocookie.net/banjokazooie/images/f/f3/Gobi_head.png"
    },
    "description":"Oi! My precious rank.",
    "field":{
      "description":"Will you stop that! It took me ages to climb the leaderboard."
    }
  },
  {
    "author":{
      "name":"Croctus", "image":"https://vignette.wikia.nocookie.net/banjokazooie/images/5/57/Croctus_Icon.png"
    },
    "description":"Yummy!",
    "field":{
      "description":"Croctus liked that!"
    }
  },
  {
    "author":{
      "name":"Boggy", "image":"https://vignette.wikia.nocookie.net/banjokazooie/images/f/f7/Boggy_icon.png"
    },
    "description":"Take a look at this brand new PB!",
    "field":{
      "description":"It's got loads of features!"
    }
  },
  {
    "author":{
      "name":"Boggy", "image":"https://vignette.wikia.nocookie.net/banjokazooie/images/f/f7/Boggy_icon.png"
    },
    "description":"",
    "field":{
      "description":"You look faster already! Not sure how I can tell, but it's true!"
    }
  },
  {
    "author":{
      "name":"Jolly Roger", "image":"https://vignette.wikia.nocookie.net/banjokazooie/images/8/85/Jolly.png"
    },
    "description":"Well, really!",
    "field":{
      "description":"That was a brand new PB - have you any idea how much they cost these days?!"
    }
  }]
}